{
    "baseline": {
        "date": "20260410 13:41",
        "log": [
            "baseline-20260316.parquet",
            "baseline-20260317.parquet",
            "baseline-20260318.parquet",
            "baseline-20260319.parquet",
            "baseline-20260320.parquet",
            "baseline-20260323.parquet",
            "baseline-20260324.parquet",
            "baseline-20260325.parquet",
            "baseline-20260326.parquet",
            "baseline-20260327.parquet",
            "baseline-20260330.parquet",
            "baseline-20260331.parquet",
            "baseline-20260401.parquet",
            "baseline-20260402.parquet",
            "baseline-20260403.parquet",
            "baseline-20260406.parquet",
            "baseline-20260407.parquet",
            "baseline-20260408.parquet",
            "baseline-20260409.parquet",
            "baseline-20260410.parquet"
        ]
    },
    "market": {
        "date": "20260410 13:41"
    },
    "number": {
        "date": "20260408"
    },
    "prices": {
        "time": "20260410 13:41"
    },
    "sector": {
        "date": "20260409"
    }
}